botipy/__init__.py
botipy/cli.py
botipy/src/Makefile
botipy/src/Procfile
botipy/src/__init__.py
botipy/src/app.py
botipy/src/bot.py
botipy/src/requirements.txt
botipy/src/cog/__init__.py
botipy-0.3.1.dist-info/LICENSE
botipy-0.3.1.dist-info/METADATA
botipy-0.3.1.dist-info/WHEEL
botipy-0.3.1.dist-info/entry_points.txt
botipy-0.3.1.dist-info/top_level.txt
botipy-0.3.1.dist-info/RECORD
